Workbook

Sheet Performance
A1: metric | B1: value
A2: script | B2: Node - v0.18.0
A3: capital | B3: 50000
A4: windows | B4: 10
A5: trades | B5: =COUNT(Trades!$H$2:$H$17)
A6: from | B6: =MIN(Trades!$C$2:$C$17)
A7: to | B7: =MAX(Trades!$E$2:$E$17)
A9: net | B9: =SUM(Trades!$H$2:$H$17)
A10: net % | B10: =$B$9/$B$3
A11: gross win | B11: =SUMIF(Trades!$H$2:$H$17,">0")
A12: gross loss | B12: =-SUMIF(Trades!$H$2:$H$17,"<0")
A13: profit factor | B13: =IF($B$12=0,"",$B$11/$B$12)
A15: wins | B15: =COUNTIF(Trades!$H$2:$H$17,">0")
A16: losses | B16: =COUNTIF(Trades!$H$2:$H$17,"<0")
A17: win rate | B17: =$B$15/$B$5
A18: average win | B18: =IF($B$15=0,"",$B$11/$B$15)
A19: average loss | B19: =IF($B$16=0,"",-$B$12/$B$16)
A20: expectancy | B20: =$B$9/$B$5
A21: best | B21: =MAX(Trades!$H$2:$H$17)
A22: worst | B22: =MIN(Trades!$H$2:$H$17)
A24: max drawdown | B24: =MAX(Trades!$Q$2:$Q$17)
A25: max drawdown % | B25: =MAX(Trades!$R$2:$R$17)
A26: losing streak | B26: =MAX(Trades!$S$2:$S$17)
A27: commission | B27: =SUM(Trades!$I$2:$I$17)
A29: long trades | B29: =COUNTIF(Trades!$B$2:$B$17,"long")
A30: long net | B30: =SUMIF(Trades!$B$2:$B$17,"long",Trades!$H$2:$H$17)
A31: long win rate | B31: =IF($B$29=0,"",COUNTIFS(Trades!$B$2:$B$17,"long",Trades!$H$2:$H$17,">0")/$B$29)
A32: short trades | B32: =COUNTIF(Trades!$B$2:$B$17,"short")
A33: short net | B33: =SUMIF(Trades!$B$2:$B$17,"short",Trades!$H$2:$H$17)
A34: short win rate | B34: =IF($B$32=0,"",COUNTIFS(Trades!$B$2:$B$17,"short",Trades!$H$2:$H$17,">0")/$B$32)

Sheet Trades
A1: n | B1: side | C1: entry time | D1: entry price | E1: exit time | F1: exit price | G1: qty | H1: net pnl | I1: commission | J1: favorable | K1: adverse | L1: bars | M1: source | N1: cumulative pnl | O1: equity | P1: peak | Q1: drawdown | R1: drawdown % | S1: losing streak
A2: 1 | B2: long | C2: 46086.526 | D2: 25010.75 | E2: 46086.603 | F2: 24930.5 | G2: 3 | H2: -485.5 | I2: 4 | J2: 671.5 | K2: -483.5 | L2: 111 | M2: Node_-_v0.17.1-dev_CME_MINI_MNQ1!_2026-09-13_69c63.csv | N2: =SUM($H$2:H2) | O2: =Performance!$B$3+N2 | P2: =MAX(Performance!$B$3,O2) | Q2: =P2-O2 | R2: =IF(P2=0,0,Q2/P2) | S2: =IF(H2<0,1,0)
A3: 2 | B3: short | C3: 46125.442 | D3: 25182.5 | E3: 46125.451 | F3: 25239.25 | G3: 4 | H3: -458 | I3: 4 | J3: 178 | K3: -456 | L3: 12 | M3: Node_-_v0.17.1-dev_CME_MINI_MNQ1!_2026-09-13_58c79.csv | N3: =SUM($H$2:H3) | O3: =Performance!$B$3+N3 | P3: =MAX(P2,O3) | Q3: =P3-O3 | R3: =IF(P3=0,0,Q3/P3) | S3: =IF(H3<0,S2+1,0)
A4: 3 | B4: long | C4: 46139.455 | D4: 27378.25 | E4: 46139.792 | F4: 27436 | G4: 3 | H4: 342.5 | I4: 4 | J4: 442 | K4: -428 | L4: 426 | M4: Node_-_v0.17.1-dev_CME_MINI_MNQ1!_2026-09-13_b019e.csv | N4: =SUM($H$2:H4) | O4: =Performance!$B$3+N4 | P4: =MAX(P3,O4) | Q4: =P4-O4 | R4: =IF(P4=0,0,Q4/P4) | S4: =IF(H4<0,S3+1,0)
A5: 4 | B5: long | C5: 46149.625 | D5: 28696.25 | E5: 46149.792 | F5: 28553.5 | G5: 1 | H5: -289.5 | I5: 4 | J5: 139.5 | K5: -287.5 | L5: 180 | M5: Node_-_v0.17.1-dev_CME_MINI_MNQ1!_2026-09-13_b019e.csv | N5: =SUM($H$2:H5) | O5: =Performance!$B$3+N5 | P5: =MAX(P4,O5) | Q5: =P5-O5 | R5: =IF(P5=0,0,Q5/P5) | S5: =IF(H5<0,S4+1,0)
A6: 5 | B6: short | C6: 46162.453 | D6: 29101 | E6: 46162.469 | F6: 29195.25 | G6: 2 | H6: -381 | I6: 4 | J6: 370 | K6: -379 | L6: 24 | M6: Node_-_v0.17.1-dev_CME_MINI_MNQ1!_2026-09-13_0393c.csv | N6: =SUM($H$2:H6) | O6: =Performance!$B$3+N6 | P6: =MAX(P5,O6) | Q6: =P6-O6 | R6: =IF(P6=0,0,Q6/P6) | S6: =IF(H6<0,S5+1,0)
A7: 6 | B7: short | C7: 46162.503 | D7: 29235.5 | E7: 46162.51 | F7: 29284.75 | G7: 5 | H7: -496.5 | I7: 4 | J7: 30.5 | K7: -494.5 | L7: 11 | M7: Node_-_v0.17.1-dev_CME_MINI_MNQ1!_2026-09-13_0393c.csv | N7: =SUM($H$2:H7) | O7: =Performance!$B$3+N7 | P7: =MAX(P6,O7) | Q7: =P7-O7 | R7: =IF(P7=0,0,Q7/P7) | S7: =IF(H7<0,S6+1,0)
A8: 7 | B8: short | C8: 46183.49 | D8: 29083.25 | E8: 46183.508 | F8: 28747 | G8: 1 | H8: 668.5 | I8: 4 | J8: 670.5 | K8: -89 | L8: 27 | M8: Node_-_v0.17.1-dev_CME_MINI_MNQ1!_2026-09-13_984fa.csv | N8: =SUM($H$2:H8) | O8: =Performance!$B$3+N8 | P8: =MAX(P7,O8) | Q8: =P8-O8 | R8: =IF(P8=0,0,Q8/P8) | S8: =IF(H8<0,S7+1,0)
A9: 8 | B9: short | C9: 46184.463 | D9: 29012.25 | E9: 46184.465 | F9: 28938.5 | G9: 6 | H9: 881 | I9: 4 | J9: 883 | K9: -146 | L9: 3 | M9: Node_-_v0.17.1-dev_CME_MINI_MNQ1!_2026-09-13_984fa.csv | N9: =SUM($H$2:H9) | O9: =Performance!$B$3+N9 | P9: =MAX(P8,O9) | Q9: =P9-O9 | R9: =IF(P9=0,0,Q9/P9) | S9: =IF(H9<0,S8+1,0)
A10: 9 | B10: long | C10: 46189.442 | D10: 30808.5 | E10: 46189.472 | F10: 30750.75 | G10: 4 | H10: -466 | I10: 4 | J10: 642 | K10: -464 | L10: 42 | M10: Node_-_v0.17.1-dev_CME_MINI_MNQ1!_2026-09-13_984fa.csv | N10: =SUM($H$2:H10) | O10: =Performance!$B$3+N10 | P10: =MAX(P9,O10) | Q10: =P10-O10 | R10: =IF(P10=0,0,Q10/P10) | S10: =IF(H10<0,S9+1,0)
A11: 10 | B11: short | C11: 46197.507 | D11: 29784.5 | E11: 46197.594 | F11: 29537.75 | G11: 2 | H11: 983 | I11: 4 | J11: 985 | K11: -178 | L11: 126 | M11: Node_-_v0.17.1-dev_CME_MINI_MNQ1!_2026-09-13_8a095.csv | N11: =SUM($H$2:H11) | O11: =Performance!$B$3+N11 | P11: =MAX(P10,O11) | Q11: =P11-O11 | R11: =IF(P11=0,0,Q11/P11) | S11: =IF(H11<0,S10+1,0)
A12: 11 | B12: long | C12: 46234.472 | D12: 28194 | E12: 46234.594 | F12: 28421 | G12: 2 | H12: 904 | I12: 4 | J12: 906 | K12: -316 | L12: 176 | M12: Node_-_v0.17.1-dev_CME_MINI_MNQ1!_2026-09-13_c96c8.csv | N12: =SUM($H$2:H12) | O12: =Performance!$B$3+N12 | P12: =MAX(P11,O12) | Q12: =P12-O12 | R12: =IF(P12=0,0,Q12/P12) | S12: =IF(H12<0,S11+1,0)
A13: 12 | B13: long | C13: 46237.442 | D13: 28501.5 | E13: 46237.599 | F13: 28878.5 | G13: 1 | H13: 750 | I13: 4 | J13: 752 | K13: -173 | L13: 226 | M13: Node_-_v0.17.1-dev_CME_MINI_MNQ1!_2026-09-13_bb623.csv | N13: =SUM($H$2:H13) | O13: =Performance!$B$3+N13 | P13: =MAX(P12,O13) | Q13: =P13-O13 | R13: =IF(P13=0,0,Q13/P13) | S13: =IF(H13<0,S12+1,0)
A14: 13 | B14: long | C14: 46239.552 | D14: 29731.25 | E14: 46239.556 | F14: 29791.75 | G14: 8 | H14: 964 | I14: 4 | J14: 966 | K14: -190 | L14: 6 | M14: Node_-_v0.17.1-dev_CME_MINI_MNQ1!_2026-09-13_bb623.csv | N14: =SUM($H$2:H14) | O14: =Performance!$B$3+N14 | P14: =MAX(P13,O14) | Q14: =P14-O14 | R14: =IF(P14=0,0,Q14/P14) | S14: =IF(H14<0,S13+1,0)
... A17: 16 | B17: long | C17: 46269.617 | D17: 29484.75 | E17: 46269.646 | F17: 29517.75 | G17: 15 | H17: 986 | I17: 4 | J17: 988 | K17: -407 | L17: 42 | M17: Node_-_v0.17.1-dev_CME_MINI_MNQ1!_2026-09-13_11e6b.csv | N17: =SUM($H$2:H17) | O17: =Performance!$B$3+N17 | P17: =MAX(P16,O17) | Q17: =P17-O17 | R17: =IF(P17=0,0,Q17/P17) | S17: =IF(H17<0,S16+1,0)
